pyzure/AzureDBStream.py
pyzure/__init__.py
pyzure/core/Column.py
pyzure/core/Table.py
pyzure/core/__init__.py
pyzure/core/tools/__init__.py
pyzure/core/tools/detect_types.py
pyzure/core/tools/print_colors.py
pyzure/core/tools/progress_bar.py
pyzure-0.1.31.dist-info/METADATA
pyzure-0.1.31.dist-info/RECORD
pyzure-0.1.31.dist-info/WHEEL
pyzure-0.1.31.dist-info/top_level.txt
